{"typhoon":{"name":"KUJIRA","track":[{"time":"2003-04-08T14:00:00","epoch":1049781600,"lat":2.6,"lon":158.8,"pressure":1006,"wind":8,"gust":-99,"r7":-99,"r10":-99,"warn":0},{"time":"2003-04-08T20:00:00","epoch":1049803200,"lat":3.0,"lon":159.5,"pressure":1004,"wind":12,"gust":-99,"r7":-99,"r10":-99,"warn":0},{"time":"2003-04-09T02:00:00","epoch":1049824800,"lat":3.4,"lon":160.0,"pressure":1002,"wind":12,"gust":-99,"r7":-99,"r10":-99,"warn":0},{"time":"2003-04-09T08:00:00","epoch":1049846400,"lat":3.7,"lon":160.2,"pressure":1000,"wind":15,"gust":-99,"r7":-99,"r10":-99,"warn":0},{"time":"2003-04-09T14:00:00","epoch":1049868000,"lat":4.1,"lon":160.4,"pressure":997,"wind":18,"gust":-99,"r7":-99,"r10":-99,"warn":0},{"time":"2003-04-09T20:00:00","epoch":1049889600,"lat":4.6,"lon":160.6,"pressure":997,"wind":18,"gust":-99,"r7":-99,"r10":-99,"warn":0},{"time":"2003-04-10T02:00:00","epoch":1049911200,"lat":5.4,"lon":160.6,"pressure":997,"wind":18,"gust":-99,"r7":-99,"r10":-99,"warn":0},{"time":"2003-04-10T08:00:00","epoch":1049932800,"lat":6.5,"lon":160.4,"pressure":994,"wind":20,"gust":-99,"r7":-99,"r10":-99,"warn":0},{"time":"2003-04-10T14:00:00","epoch":1049954400,"lat":7.5,"lon":159.7,"pressure":994,"wind":20,"gust":-99,"r7":-99,"r10":-99,"warn":0},{"time":"2003-04-10T20:00:00","epoch":1049976000,"lat":8.1,"lon":159.0,"pressure":994,"wind":20,"gust":-99,"r7":-99,"r10":-99,"warn":0},{"time":"2003-04-11T02:00:00","epoch":1049997600,"lat":8.6,"lon":158.3,"pressure":994,"wind":20,"gust":-99,"r7":-99,"r10":-99,"warn":0},{"time":"2003-04-11T08:00:00","epoch":1050019200,"lat":9.0,"lon":158.0,"pressure":-99,"wind":18,"gust":-99,"r7":-99,"r10":-99,"warn":0},{"time":"2003-04-11T14:00:00","epoch":1050040800,"lat":9.6,"lon":156.7,"pressure":-99,"wind":18,"gust":-99,"r7":-99,"r10":-99,"warn":0},{"time":"2003-04-11T20:00:00","epoch":1050062400,"lat":9.8,"lon":156.0,"pressure":-99,"wind":18,"gust":-99,"r7":-99,"r10":-99,"warn":0},{"time":"2003-04-12T02:00:00","epoch":1050084000,"lat":9.9,"lon":155.3,"pressure":-99,"wind":20,"gust":-99,"r7":-99,"r10":-99,"warn":0},{"time":"2003-04-12T08:00:00","epoch":1050105600,"lat":9.9,"lon":154.2,"pressure":-99,"wind":23,"gust":-99,"r7":-99,"r10":-99,"warn":0},{"time":"2003-04-12T14:00:00","epoch":1050127200,"lat":10.0,"lon":152.9,"pressure":-99,"wind":23,"gust":-99,"r7":-99,"r10":-99,"warn":0},{"time":"2003-04-12T20:00:00","epoch":1050148800,"lat":10.1,"lon":152.3,"pressure":-99,"wind":23,"gust":-99,"r7":-99,"r10":-99,"warn":0},{"time":"2003-04-13T02:00:00","epoch":1050170400,"lat":10.1,"lon":151.5,"pressure":-99,"wind":25,"gust":-99,"r7":-99,"r10":-99,"warn":0},{"time":"2003-04-13T08:00:00","epoch":1050192000,"lat":10.1,"lon":150.8,"pressure":-99,"wind":28,"gust":-99,"r7":-99,"r10":-99,"warn":0},{"time":"2003-04-13T14:00:00","epoch":1050213600,"lat":10.1,"lon":149.9,"pressure":-99,"wind":28,"gust":-99,"r7":-99,"r10":-99,"warn":0},{"time":"2003-04-13T20:00:00","epoch":1050235200,"lat":10.1,"lon":149.1,"pressure":-99,"wind":28,"gust":-99,"r7":-99,"r10":-99,"warn":0},{"time":"2003-04-14T02:00:00","epoch":1050256800,"lat":10.3,"lon":148.3,"pressure":-99,"wind":30,"gust":-99,"r7":-99,"r10":-99,"warn":0},{"time":"2003-04-14T08:00:00","epoch":1050278400,"lat":10.4,"lon":147.3,"pressure":-99,"wind":33,"gust":-99,"r7":-99,"r10":-99,"warn":0},{"time":"2003-04-14T14:00:00","epoch":1050300000,"lat":10.6,"lon":146.1,"pressure":-99,"wind":35,"gust":-99,"r7":-99,"r10":-99,"warn":0},{"time":"2003-04-14T20:00:00","epoch":1050321600,"lat":10.7,"lon":145.2,"pressure":-99,"wind":40,"gust":-99,"r7":-99,"r10":-99,"warn":0},{"time":"2003-04-15T02:00:00","epoch":1050343200,"lat":11.1,"lon":143.8,"pressure":-99,"wind":40,"gust":-99,"r7":-99,"r10":-99,"warn":0},{"time":"2003-04-15T08:00:00","epoch":1050364800,"lat":11.5,"lon":142.3,"pressure":-99,"wind":45,"gust":-99,"r7":-99,"r10":-99,"warn":0},{"time":"2003-04-15T14:00:00","epoch":1050386400,"lat":11.9,"lon":140.9,"pressure":-99,"wind":45,"gust":-99,"r7":-99,"r10":-99,"warn":0},{"time":"2003-04-15T20:00:00","epoch":1050408000,"lat":12.3,"lon":139.5,"pressure":-99,"wind":48,"gust":-99,"r7":-99,"r10":-99,"warn":0},{"time":"2003-04-16T02:00:00","epoch":1050429600,"lat":12.6,"lon":138.2,"pressure":-99,"wind":48,"gust":-99,"r7":-99,"r10":-99,"warn":0},{"time":"2003-04-16T08:00:00","epoch":1050451200,"lat":13.0,"lon":137.0,"pressure":-99,"wind":51,"gust":-99,"r7":-99,"r10":-99,"warn":0},{"time":"2003-04-16T14:00:00","epoch":1050472800,"lat":13.5,"lon":136.0,"pressure":-99,"wind":51,"gust":-99,"r7":-99,"r10":-99,"warn":0},{"time":"2003-04-16T20:00:00","epoch":1050494400,"lat":13.7,"lon":135.2,"pressure":-99,"wind":51,"gust":-99,"r7":-99,"r10":-99,"warn":0},{"time":"2003-04-17T02:00:00","epoch":1050516000,"lat":13.9,"lon":134.3,"pressure":-99,"wind":48,"gust":-99,"r7":-99,"r10":-99,"warn":0},{"time":"2003-04-17T08:00:00","epoch":1050537600,"lat":14.0,"lon":133.6,"pressure":-99,"wind":45,"gust":-99,"r7":-99,"r10":-99,"warn":0},{"time":"2003-04-17T14:00:00","epoch":1050559200,"lat":13.9,"lon":132.8,"pressure":-99,"wind":45,"gust":-99,"r7":-99,"r10":-99,"warn":0},{"time":"2003-04-17T20:00:00","epoch":1050580800,"lat":13.7,"lon":132.1,"pressure":-99,"wind":45,"gust":-99,"r7":-99,"r10":-99,"warn":0},{"time":"2003-04-18T02:00:00","epoch":1050602400,"lat":13.6,"lon":131.3,"pressure":-99,"wind":45,"gust":-99,"r7":-99,"r10":-99,"warn":0},{"time":"2003-04-18T08:00:00","epoch":1050624000,"lat":13.6,"lon":130.5,"pressure":-99,"wind":45,"gust":-99,"r7":-99,"r10":-99,"warn":0},{"time":"2003-04-18T14:00:00","epoch":1050645600,"lat":13.5,"lon":130.0,"pressure":940,"wind":45,"gust":55,"r7":250,"r10":100,"warn":0},{"time":"2003-04-18T20:00:00","epoch":1050667200,"lat":13.6,"lon":129.6,"pressure":-99,"wind":45,"gust":-99,"r7":-99,"r10":-99,"warn":0},{"time":"2003-04-19T02:00:00","epoch":1050688800,"lat":13.9,"lon":129.1,"pressure":-99,"wind":45,"gust":-99,"r7":-99,"r10":-99,"warn":0},{"time":"2003-04-19T08:00:00","epoch":1050710400,"lat":14.1,"lon":128.8,"pressure":-99,"wind":43,"gust":-99,"r7":-99,"r10":-99,"warn":0},{"time":"2003-04-19T14:00:00","epoch":1050732000,"lat":14.7,"lon":128.3,"pressure":-99,"wind":43,"gust":-99,"r7":-99,"r10":-99,"warn":0},{"time":"2003-04-19T20:00:00","epoch":1050753600,"lat":15.1,"lon":127.9,"pressure":-99,"wind":43,"gust":-99,"r7":-99,"r10":-99,"warn":0},{"time":"2003-04-20T02:00:00","epoch":1050775200,"lat":15.7,"lon":127.3,"pressure":-99,"wind":40,"gust":-99,"r7":-99,"r10":-99,"warn":0},{"time":"2003-04-20T08:00:00","epoch":1050796800,"lat":16.2,"lon":126.7,"pressure":-99,"wind":40,"gust":-99,"r7":-99,"r10":-99,"warn":0},{"time":"2003-04-20T14:00:00","epoch":1050818400,"lat":16.7,"lon":126.1,"pressure":-99,"wind":40,"gust":-99,"r7":-99,"r10":-99,"warn":0},{"time":"2003-04-20T20:00:00","epoch":1050840000,"lat":17.1,"lon":125.6,"pressure":-99,"wind":43,"gust":-99,"r7":-99,"r10":-99,"warn":0},{"time":"2003-04-21T02:00:00","epoch":1050861600,"lat":18.0,"lon":125.1,"pressure":-99,"wind":43,"gust":-99,"r7":-99,"r10":-99,"warn":0},{"time":"2003-04-21T08:00:00","epoch":1050883200,"lat":18.3,"lon":124.6,"pressure":-99,"wind":43,"gust":-99,"r7":-99,"r10":-99,"warn":1},{"time":"2003-04-21T14:00:00","epoch":1050904800,"lat":18.7,"lon":124.3,"pressure":-99,"wind":43,"gust":-99,"r7":-99,"r10":-99,"warn":1},{"time":"2003-04-21T20:00:00","epoch":1050926400,"lat":19.3,"lon":124.2,"pressure":-99,"wind":38,"gust":-99,"r7":-99,"r10":-99,"warn":1},{"time":"2003-04-22T02:00:00","epoch":1050948000,"lat":19.5,"lon":124.0,"pressure":-99,"wind":35,"gust":-99,"r7":-99,"r10":-99,"warn":2},{"time":"2003-04-22T08:00:00","epoch":1050969600,"lat":19.7,"lon":123.6,"pressure":-99,"wind":30,"gust":-99,"r7":-99,"r10":-99,"warn":2},{"time":"2003-04-22T14:00:00","epoch":1050991200,"lat":20.2,"lon":123.2,"pressure":-99,"wind":28,"gust":-99,"r7":-99,"r10":-99,"warn":2},{"time":"2003-04-22T20:00:00","epoch":1051012800,"lat":20.5,"lon":123.2,"pressure":-99,"wind":28,"gust":-99,"r7":-99,"r10":-99,"warn":2},{"time":"2003-04-23T02:00:00","epoch":1051034400,"lat":20.8,"lon":123.0,"pressure":-99,"wind":25,"gust":-99,"r7":-99,"r10":-99,"warn":2},{"time":"2003-04-23T08:00:00","epoch":1051056000,"lat":20.8,"lon":122.5,"pressure":-99,"wind":23,"gust":-99,"r7":-99,"r10":-99,"warn":2},{"time":"2003-04-23T14:00:00","epoch":1051077600,"lat":20.8,"lon":122.3,"pressure":-99,"wind":18,"gust":-99,"r7":-99,"r10":-99,"warn":2},{"time":"2003-04-23T20:00:00","epoch":1051099200,"lat":21.1,"lon":122.4,"pressure":-99,"wind":18,"gust":-99,"r7":-99,"r10":-99,"warn":2},{"time":"2003-04-24T02:00:00","epoch":1051120800,"lat":21.6,"lon":122.5,"pressure":-99,"wind":18,"gust":-99,"r7":-99,"r10":-99,"warn":2},{"time":"2003-04-24T08:00:00","epoch":1051142400,"lat":22.0,"lon":122.6,"pressure":-99,"wind":18,"gust":-99,"r7":-99,"r10":-99,"warn":2},{"time":"2003-04-24T14:00:00","epoch":1051164000,"lat":23.1,"lon":123.2,"pressure":-99,"wind":18,"gust":-99,"r7":-99,"r10":-99,"warn":2},{"time":"2003-04-24T20:00:00","epoch":1051185600,"lat":25.0,"lon":124.5,"pressure":-99,"wind":18,"gust":-99,"r7":-99,"r10":-99,"warn":2},{"time":"2003-04-25T02:00:00","epoch":1051207200,"lat":26.8,"lon":125.3,"pressure":-99,"wind":18,"gust":-99,"r7":-99,"r10":-99,"warn":3},{"time":"2003-04-25T08:00:00","epoch":1051228800,"lat":29.2,"lon":127.2,"pressure":-99,"wind":18,"gust":-99,"r7":-99,"r10":-99,"warn":0},{"time":"2003-04-25T14:00:00","epoch":1051250400,"lat":32.1,"lon":130.1,"pressure":1000,"wind":15,"gust":-99,"r7":-99,"r10":-99,"warn":0},{"time":"2003-04-25T20:00:00","epoch":1051272000,"lat":34.2,"lon":134.0,"pressure":1000,"wind":15,"gust":-99,"r7":-99,"r10":-99,"warn":0}]},"stations":{},"hourlyData":{}}